shepherd_herd/__init__.py
shepherd_herd/herd.py
shepherd_herd/herd_cli.py
shepherd_herd/logger.py
tests/__init__.py
tests/conftest.py
tests/test_cli_basic.py
tests/test_cli_emu.py
tests/test_cli_hrv.py
tests/test_cli_prog_openocd.py
tests/test_cli_programmer.py
tests/test_herd_class.py
shepherd_herd-0.9.3.dist-info/METADATA
shepherd_herd-0.9.3.dist-info/WHEEL
shepherd_herd-0.9.3.dist-info/entry_points.txt
shepherd_herd-0.9.3.dist-info/top_level.txt
shepherd_herd-0.9.3.dist-info/zip-safe
shepherd_herd-0.9.3.dist-info/RECORD
