Metadata-Version: 2.4
Name: shepherd_herd
Version: 0.9.3
Summary: Synchronized Energy Harvesting Emulator and Recorder CLI
Author-email: Kai Geissdoerfer <kai.geissdoerfer@tu-dresden.de>, Ingmar Splitt <ingmar.splitt@tu-dresden.de>
Maintainer-email: Ingmar Splitt <ingmar.splitt@tu-dresden.de>
License: MIT
Project-URL: Homepage, https://pypi.org/project/shepherd-herd
Project-URL: Documentation, https://nes-lab.github.io/shepherd
Project-URL: Issues, https://github.com/nes-lab/shepherd/issues
Project-URL: Source, https://github.com/nes-lab/shepherd
Keywords: testbed,beaglebone,pru,batteryless,energyharvesting,solar
Platform: unix
Platform: linux
Platform: osx
Platform: cygwin
Platform: win32
Platform: win64
Classifier: Development Status :: 5 - Production/Stable
Classifier: Intended Audience :: Developers
Classifier: Intended Audience :: Information Technology
Classifier: Intended Audience :: Science/Research
Classifier: Programming Language :: Python :: 3
Classifier: Programming Language :: Python :: 3.10
Classifier: Programming Language :: Python :: 3.11
Classifier: Programming Language :: Python :: 3.12
Classifier: Programming Language :: Python :: 3.13
Classifier: License :: OSI Approved :: MIT License
Classifier: Operating System :: OS Independent
Classifier: Natural Language :: English
Requires-Python: >=3.10
Requires-Dist: shepherd-core[elf,inventory]>=2025.06.4
Requires-Dist: click
Requires-Dist: numpy
Requires-Dist: fabric
Requires-Dist: pyYAML
Requires-Dist: tqdm
Provides-Extra: dev
Requires-Dist: twine; extra == "dev"
Requires-Dist: pre-commit; extra == "dev"
Requires-Dist: pyright; extra == "dev"
Requires-Dist: ruff; extra == "dev"
Provides-Extra: test
Requires-Dist: pytest; extra == "test"
Requires-Dist: pytest-timeout; extra == "test"
Requires-Dist: pytest-click; extra == "test"
Requires-Dist: shepherd-data; extra == "test"
